LICENSE
MANIFEST.in
README.md
setup.py
rsxr/compiler.py
rsxr/icon.ico
rsxr/icon.png
rsxr/icon_alternative.ico
rsxr/icon_alternative.png
rsxr/logo.png
rsxr/main.py
rsxr.egg-info/PKG-INFO
rsxr.egg-info/SOURCES.txt
rsxr.egg-info/dependency_links.txt
rsxr.egg-info/entry_points.txt
rsxr.egg-info/requires.txt
rsxr.egg-info/top_level.txt
rsxr/asm/__chkstk.s
rsxr/bin/openvr_api.dll
rsxr/include/rsxr-rvr/constants.rsxrh
rsxr/include/rsxr-rvr/init.rsxrh
rsxr/include/rsxr-rvr/rsxr-rvr.rsxrh
rsxr/include/rsxrgl/constants.rsxrh
rsxr/include/rsxrgl/init.rsxrh
rsxr/include/rsxrgl/rsxrgl.rsxrh
rsxr/include/rsxrglfw/init.rsxrh
rsxr/include/rsxrglfw/rsxrglfw.rsxrh
rsxr/include/rsxrio/init.rsxrh
rsxr/include/rsxrio/rsxrio.rsxrh
rsxr/include/rsxrio/stdio.rsxrh
rsxr/include/rsxrmath/init.rsxrh
rsxr/include/rsxrmath/rsxrmath.rsxrh
rsxr/lib/libglad.a
rsxr/lib/libglfw3.a
rsxr/lib/libraylib.a
rsxr/lib/openvr_api.lib