Metadata-Version: 2.1
Name: rsxr
Version: 0.0.2
Summary: A compiled statically typed multi paradigm general purpose programming language designed for cross platform applications.
Home-page: https://github.com/Aermoss/RSX-R
Author: Yusuf Rencber
Author-email: aermoss.0@gmail.com
License: MIT
Platform: UNKNOWN
License-File: LICENSE
